{
  "startDate": "2025-04-21",
  "title": "Încheiem această călătorie prin Săptămâna Patimilor din 2025 cu gândul la Cuvântul lui Dumnezeu",
  "content": [
    {
      "text": "„Toată Scriptura este insuflată de Dumnezeu și de folos ca să învețe, să mustre, să îndrepte, să dea înțelepciune în neprihănire.\"",
      "reference": "2 Timotei 3:16"
    },
    {
      "text": "Să continuăm să explorăm bogățiile Cuvântului lui Dumnezeu și să facem din acesta călăuza noastră zilnică, amintindu-ne de cuvintele lui Isus:",
      "reference": ""
    },
    {
      "text": "„Cercetați Scripturile, pentru că socotiți că în ele aveți viața veșnică, dar tocmai ele mărturisesc despre Mine.\"",
      "reference": "Ioan 5:39"
    }
  ]
}
